setup.py
jps/__init__.py
jps/forwarder.py
jps/publisher.py
jps/subscriber.py
jps/tools.py
jps.egg-info/PKG-INFO
jps.egg-info/SOURCES.txt
jps.egg-info/dependency_links.txt
jps.egg-info/entry_points.txt
jps.egg-info/requires.txt
jps.egg-info/top_level.txt