Metadata-Version: 1.0
Name: jps
Version: 0.0.1
Summary: json pub/sub using zmq
Home-page: http://github.com/OTL/jps
Author: Takashi Ogura
Author-email: t.ogura@gmail.com
License: UNKNOWN
Platform: UNKNOWN
